MANIFEST.in
README.md
requirements.txt
setup.cfg
setup.py
versioneer.py
botcity/document_processing/__init__.py
botcity/document_processing/_version.py
botcity/document_processing/geometry.py
botcity/document_processing/parser/__init__.py
botcity/document_processing/parser/document.py
botcity/document_processing/parser/entry.py
botcity/document_processing/parser/matcher.py
botcity/document_processing/pdf/__init__.py
botcity/document_processing/pdf/document-processing-1.3.3.jar
botcity/document_processing/pdf/pdfbox-app-2.0.19.jar
botcity/document_processing/pdf/pdfreader.py
botcity_documents.egg-info/PKG-INFO
botcity_documents.egg-info/SOURCES.txt
botcity_documents.egg-info/dependency_links.txt
botcity_documents.egg-info/requires.txt
botcity_documents.egg-info/top_level.txt
tests/test_import.py
tests/test_parse_pdf.py