Metadata-Version: 2.1
Name: botcity-documents
Version: 0.5.0
Home-page: https://bitbucket.org/botcitydev/botcity-documents-python
Requires-Python: >=3.7
